mpplot/__init__.py
mpplot/mpplot.py
mpplot-0.4.dist-info/LICENSE
mpplot-0.4.dist-info/METADATA
mpplot-0.4.dist-info/WHEEL
mpplot-0.4.dist-info/entry_points.txt
mpplot-0.4.dist-info/top_level.txt
mpplot-0.4.dist-info/RECORD
