Metadata-Version: 2.1
Name: mpplot
Version: 0.4
Summary: mpplot that connect matplotlib and matlab
Author: kevin
Author-email: kevin2059@163.com
License: MIT
License-File: LICENSE
Requires-Dist: h5py >=3.12.1
Requires-Dist: matplotlib >=3.9.2
